grass_session/__init__.py
grass_session/session.py
grass_session/session_works.py
tests/__init__.py
tests/grassbin_test.py
tests/platformname_test.py
tests/session_test.py
tests/test_no_with.py
tests/test_platformname.py
tests/test_session.py
tests/test_with.py
tests/tst_tif.py
grass_session-0.5.dist-info/LICENSE
grass_session-0.5.dist-info/METADATA
grass_session-0.5.dist-info/WHEEL
grass_session-0.5.dist-info/top_level.txt
grass_session-0.5.dist-info/RECORD
