Metadata-Version: 2.1
Name: grass-session
Version: 0.5
Summary: GRASS GIS session utilities
Home-page: https://github.com/zarch/grass-session
Author: Pietro Zambelli
Author-email: peter.zamb@gmail.com
License: UNKNOWN
Platform: UNKNOWN
Classifier: Development Status :: 4 - Beta
Classifier: Programming Language :: Python :: 2
Classifier: Programming Language :: Python :: 3
Classifier: License :: OSI Approved :: GNU General Public License v3 or later (GPLv3+)
